example.py
pos_json_decoder/__init__.py
pos_json_decoder-0.0.1.dist-info/licenses/LICENSE
pos_json_decoder-0.0.1.dist-info/METADATA
pos_json_decoder-0.0.1.dist-info/WHEEL
pos_json_decoder-0.0.1.dist-info/top_level.txt
pos_json_decoder-0.0.1.dist-info/RECORD
