Metadata-Version: 2.4
Name: pos-json-decoder
Version: 0.0.1
Summary: A JSON Decoder with document position annotated elements
Author-email: Andrew Allen <a2intl@gmail.com>
License-Expression: MIT
Project-URL: Homepage, https://github.com/a2intl/pos-json-decoder
Project-URL: Issues, https://github.com/a2intl/pos-json-decoder/issues
Classifier: Programming Language :: Python :: 3
Classifier: Operating System :: OS Independent
Classifier: Topic :: File Formats :: JSON
Requires-Python: >=3.8
License-File: LICENSE
Dynamic: license-file
